ansiplus/__init__.py
ansiplus/ansi/colors.py
ansiplus/ansi/cursor.py
ansiplus/ansi/erase.py
ansiplus/ansi/styles.py
ansiplus/commands/color2ansi.py
ansiplus/commands/colortext.py
ansiplus/commands/cursorcontrols.py
ansiplus/commands/styletext.py
ansiplus/tools/colorids.py
ansiplus/tools/colors.py
ansiplus/tools/styles.py
ansiplus/tools/testinput.py
ansiplus/uiHandler/validateinput.py
ansiplus/utils/promptColorer.py
ansiplus/utils/validatecolors.py
ansiplus-3.1.dist-info/LICENSE
ansiplus-3.1.dist-info/METADATA
ansiplus-3.1.dist-info/WHEEL
ansiplus-3.1.dist-info/top_level.txt
ansiplus-3.1.dist-info/RECORD
