Metadata-Version: 2.1
Name: ansiplus
Version: 3.1
Summary: A Python package designed to enhance code readability and CLI experience.
Home-page: https://github.com/xyzpw/ansiplus/
Author: xyzpw
Maintainer: xyzpw
License: MIT
Keywords: ansi,cursor,style,color
Classifier: Operating System :: POSIX :: Linux
Classifier: Topic :: Utilities
Classifier: Topic :: Terminals
Classifier: Environment :: Console
Classifier: Intended Audience :: Developers
Classifier: Programming Language :: Python :: 3.10
Classifier: Programming Language :: Python :: 3.11
Classifier: Programming Language :: Python :: 3.12
License-File: LICENSE
